{
  "type":  "crystal:crystal_dimension_type",
  "generator": {
    "type": "minecraft:noise",
    "settings": "minecraft:overworld",
    "biome_source": {
      "type": "minecraft:multi_noise",
      "biomes": [
        {
          "biome": "crystal:dark_tree",
          "parameters": {
            "temperature": [
              -0.15,
              0.2
            ],
            "humidity": [
              0.3,
              1
            ],
            "continentalness": [
              0.03,
              0.3
            ],
            "erosion": [
              -0.78,
              -0.375
            ],
            "weirdness": [
              -0.85,
              0.2
            ],
            "depth": 0,
            "offset": 0
          }
        }
      ]
    }
  }
}
